{"tjyozaFbrKUctHojoqAG1Q==":"piedras-con-flor-zen-500x334.jpg","IKCi+ViVHtbqnkQiu9UTMg==":"eqilibrio-1080x567.jpg","JWu82hnfY/FTAGcrIcWqNA==":"slide1-840x464.png","Hymgx1g/bUdOw9CT0N2BQQ==":"7edc024d829b883e00870c114d8df8f0-831x606.jpg","4Uv1xuB7zBe+Q1/FL/NM4g==":"eqilibrio-1200x630.jpg","/L2rk6BQaKHyJ1z/N4uqpA==":"mindfulness-e-equilibrio-emocional3-815x409.jpg","rLPNgaNgi3LFHmN5IhOakw==":"mbr-1080x540.jpg","FSH4o/xjh9u9EVU6cIn0eA==":"mbr-1920x960.jpg","310/RUZz0j/tSC5g5kRPFQ==":"mbr-1080x720.jpg","kJktIxlRX585bbeOImYztg==":"mbr-1920x1280.jpg"}